setup.cfg
setup.py
NimbusTSAPI/__init__.py
NimbusTSAPI/nimbustsapiexception.py
NimbusTSAPI/resultset.py
NimbusTSAPI/tsapi.py
NimbusTSAPI.egg-info/PKG-INFO
NimbusTSAPI.egg-info/SOURCES.txt
NimbusTSAPI.egg-info/dependency_links.txt
NimbusTSAPI.egg-info/requires.txt
NimbusTSAPI.egg-info/top_level.txt