Metadata-Version: 2.1
Name: NimbusTSAPI
Version: 0.2
Summary: Volue's Nimbus TS API GraphQL webservice python parser
Home-page: https://github.com/gsmari/NimbusTSAPI
Download-URL: https://github.com/gsmari/NimbusTSAPI/archive/0.2.tar.gz
Author: Gudmundur Smari Gudmundsson
Author-email: gummismari@gummismari.com
License: MIT
Keywords: nimbus,time series,API web service,hydropower software
Classifier: Development Status :: 3 - Alpha
Classifier: Intended Audience :: Developers
Classifier: Topic :: Software Development :: Build Tools
Classifier: License :: OSI Approved :: MIT License
Classifier: Programming Language :: Python :: 3
Classifier: Programming Language :: Python :: 3.8
Classifier: Programming Language :: Python :: 3.9
Classifier: Programming Language :: Python :: 3.10
Classifier: Programming Language :: Python :: 3.11
